djing/__init__.py
djing/apps.py
djing/core/__init__.py
djing/core/__init__.pyi
djing/core/actions/__init__.py
djing/core/actions/__init__.pyi
djing/core/actions/api.cpython-311-x86_64-linux-gnu.so
djing/core/actions/api.pyi
djing/core/actions/web.cpython-311-x86_64-linux-gnu.so
djing/core/actions/web.pyi
djing/core/application.cpython-311-x86_64-linux-gnu.so
djing/core/application.pyi
djing/core/commands/__init__.py
djing/core/commands/__init__.pyi
djing/core/commands/handle_publish.cpython-311-x86_64-linux-gnu.so
djing/core/commands/handle_publish.pyi
djing/core/decorators/__init__.py
djing/core/decorators/__init__.pyi
djing/core/decorators/access_required.cpython-311-x86_64-linux-gnu.so
djing/core/decorators/access_required.pyi
djing/core/decorators/ensure_published.cpython-311-x86_64-linux-gnu.so
djing/core/decorators/ensure_published.pyi
djing/core/djing_admin/__init__.py
djing/core/djing_admin/__init__.pyi
djing/core/djing_admin/config.cpython-311-x86_64-linux-gnu.so
djing/core/djing_admin/config.pyi
djing/core/inertia_app.cpython-311-x86_64-linux-gnu.so
djing/core/inertia_app.pyi
djing/core/libs/helpers.cpython-311-x86_64-linux-gnu.so
djing/core/license.cpython-311-x86_64-linux-gnu.so
djing/core/license.pyi
djing/core/middleware.cpython-311-x86_64-linux-gnu.so
djing/core/middleware.pyi
djing/core/rules/__init__.py
djing/core/rules/__init__.pyi
djing/core/rules/exists.cpython-311-x86_64-linux-gnu.so
djing/core/rules/exists.pyi
djing/core/urls.cpython-311-x86_64-linux-gnu.so
djing/core/urls.pyi
djing/djing_ui/package-lock.json
djing/djing_ui/package.json
djing/djing_ui/postcss.config.js
djing/djing_ui/public/vite.svg
djing/djing_ui/src/assets/vue.svg
djing/djing_ui/src/components/Framwork.vue
djing/djing_ui/src/index.css
djing/djing_ui/src/index.html
djing/djing_ui/src/main.jsx
djing/djing_ui/src/pages/Account/Login.vue
djing/djing_ui/src/pages/Errors/NotPublished.vue
djing/djing_ui/src/pages/Home.vue
djing/djing_ui/src/pages/Index.vue
djing_admin-0.3.3.dist-info/LICENSE.md
djing_admin-0.3.3.dist-info/METADATA
djing_admin-0.3.3.dist-info/WHEEL
djing_admin-0.3.3.dist-info/RECORD
