Metadata-Version: 2.1
Name: djing-admin
Version: 0.3.3
Summary: djing admin panel
License: MIT
Author: Krunal Dodiya
Author-email: kunal.dodiya1@gmail.com
Requires-Python: >=3.10,<4.0
Classifier: License :: OSI Approved :: MIT License
Classifier: Programming Language :: Python :: 3
Classifier: Programming Language :: Python :: 3.10
Classifier: Programming Language :: Python :: 3.11
Classifier: Programming Language :: Python :: 3.12
Requires-Dist: click (>=8.1.7,<9.0.0)
Requires-Dist: data-guard (>=0.0.4,<0.0.5)
Requires-Dist: django (>=5.1.1,<6.0.0)
Requires-Dist: django-ninja (>=1.3.0,<2.0.0)
Requires-Dist: django-vite (>=3.0.4,<4.0.0)
Requires-Dist: inertia-django (>=0.6.0,<0.7.0)
Requires-Dist: whitenoise (>=6.7.0,<7.0.0)
Project-URL: documentation, https://djing-admin.gitbook.io/docs
Project-URL: homepage, https://www.proalgotrader.com
Project-URL: repository, https://github.com/krunaldodiya/djing-admin
